smithwilson/__init__.py
smithwilson/core.py
smithwilson/tests/__init__.py
smithwilson/tests/test_core.py
smithwilson-0.2.0.dist-info/LICENSE
smithwilson-0.2.0.dist-info/METADATA
smithwilson-0.2.0.dist-info/WHEEL
smithwilson-0.2.0.dist-info/top_level.txt
smithwilson-0.2.0.dist-info/RECORD
