Metadata-Version: 2.1
Name: smithwilson
Version: 0.2.0
Summary: Implementation of the Smith-Wilson yield curve fitting algorithm in Python for interpolations and extrapolations of zero-coupon bond rates
Home-page: https://github.com/simicd/smith-wilson-py.git
Author: Dejan Simic
License: UNKNOWN
Platform: UNKNOWN
Classifier: Programming Language :: Python :: 3.7
Classifier: Programming Language :: Python :: 3.8
Classifier: Programming Language :: Python :: 3.9
Classifier: Programming Language :: Python :: 3.10
Classifier: License :: OSI Approved :: MIT License
Classifier: Operating System :: OS Independent
Requires-Python: >=3.7
License-File: LICENSE
Requires-Dist: numpy (>=1.21.5)
Requires-Dist: scipy (>=1.7.0)
